[{"site_code":"danatogel","site_title":"Danatogel","site_is_active":"Y","site_server_uptime":"2022-12-01 16:25:08"},{"site_code":"dingdongtogel","site_title":"Dingdongtogel","site_is_active":"Y","site_server_uptime":"2022-12-01 16:25:04"},{"site_code":"fiatogel","site_title":"Fiatogel","site_is_active":"Y","site_server_uptime":"2022-12-01 16:25:02"},{"site_code":"gengtogel","site_title":"Gengtogel","site_is_active":"Y","site_server_uptime":"2022-12-01 16:25:04"},{"site_code":"goltogel","site_title":"Goltogel","site_is_active":"Y","site_server_uptime":"2022-12-01 16:25:03"},{"site_code":"hometogel","site_title":"Hometogel","site_is_active":"Y","site_server_uptime":"2022-12-01 16:25:11"},{"site_code":"indrabet","site_title":"Indrabet","site_is_active":"Y","site_server_uptime":"2022-12-01 14:06:00"},{"site_code":"indratogel","site_title":"Indratogel","site_is_active":"Y","site_server_uptime":"2022-12-01 16:25:03"},{"site_code":"jonitogel","site_title":"Jonitogel","site_is_active":"Y","site_server_uptime":"2022-12-01 16:25:05"},{"site_code":"linetogel","site_title":"Linetogel","site_is_active":"Y","site_server_uptime":"2022-12-01 16:25:05"},{"site_code":"lunatogel","site_title":"Lunatogel","site_is_active":"Y","site_server_uptime":"2022-12-01 16:25:05"},{"site_code":"mariatogel","site_title":"Mariatogel","site_is_active":"Y","site_server_uptime":"2022-12-01 16:25:04"},{"site_code":"nanastogel","site_title":"Nanastogel","site_is_active":"Y","site_server_uptime":"2022-12-01 16:25:08"},{"site_code":"oppatogel","site_title":"Oppatogel","site_is_active":"Y","site_server_uptime":"2022-12-01 16:25:05"},{"site_code":"partaitogel","site_title":"Partaitogel","site_is_active":"Y","site_server_uptime":"2022-12-01 16:25:05"},{"site_code":"patihtogel","site_title":"Patihtogel","site_is_active":"Y","site_server_uptime":"2022-12-01 16:25:04"},{"site_code":"protogel","site_title":"Protogel","site_is_active":"Y","site_server_uptime":"2022-12-01 16:25:04"},{"site_code":"pwvip4d","site_title":"PwVip4D","site_is_active":"Y","site_server_uptime":"2022-12-01 16:25:03"},{"site_code":"situstogel","site_title":"Situstogel","site_is_active":"Y","site_server_uptime":"2022-12-01 16:25:04"},{"site_code":"togelon","site_title":"Togelon","site_is_active":"Y","site_server_uptime":"2022-12-01 16:25:04"},{"site_code":"togelup","site_title":"Togelup","site_is_active":"Y","site_server_uptime":"2022-12-01 16:25:04"},{"site_code":"udintogel","site_title":"Udintogel","site_is_active":"Y","site_server_uptime":"2022-12-01 16:25:05"},{"site_code":"wdbosbet","site_title":"WDBos","site_is_active":"Y","site_server_uptime":"2022-12-01 13:42:31"},{"site_code":"yoktogel","site_title":"Yoktogel","site_is_active":"Y","site_server_uptime":"2022-12-01 16:25:04"},{"site_code":"yowestogel","site_title":"Yowestogel","site_is_active":"Y","site_server_uptime":"2022-12-01 16:25:05"},{"site_code":"ziatogel","site_title":"Ziatogel","site_is_active":"Y","site_server_uptime":"2022-12-01 16:25:05"}]